Metadata-Version: 2.4
Name: local_notebooklm
Version: 1.2.2
Summary: A local notebook implementation
Home-page: https://github.com/Goekdeniz-Guelmez/Local-NotebookLM
Author: Gökdeniz Gülmez
Author-email: Gökdeniz Gülmez <goekdenizguelmez@gmail.com>
License: Apache-2.0
Project-URL: Homepage, https://github.com/Goekdeniz-Guelmez//Local-NotebookLM
Project-URL: Bug Tracker, https://github.com/Goekdeniz-Guelmez//Local-NotebookLM/issues
Classifier: Programming Language :: Python :: 3.12
Classifier: License :: OSI Approved :: Apache Software License
Classifier: Operating System :: OS Independent
Requires-Python: >=3.12
License-File: LICENSE
Requires-Dist: PyPDF2
Requires-Dist: tqdm
Requires-Dist: openai
Requires-Dist: soundfile
Requires-Dist: fastapi
Requires-Dist: uvicorn
Requires-Dist: python-multipart
Requires-Dist: numpy
Requires-Dist: requests
Requires-Dist: pathlib
Requires-Dist: google-genai
Requires-Dist: elevenlabs
Requires-Dist: anthropic
Requires-Dist: gradio
Dynamic: author
Dynamic: home-page
Dynamic: license-file
Dynamic: requires-python
